Workbook

Sheet Budget
A1: Monthly Budget Plan · Joshua Melville · 2026
A2: Monthly Take-Home (TTD) | B2: 7862.36 | C2: 1 | D2: ← Update B2 if your income changes
A4: Category | B4: Budget (TTD) | C4: % of Income | D4: Notes
A5: Fixed Commitments
A6: House Contribution | B6: 1000 | C6: =B6/$B$2 -> 0.12718827 | D6: Bills & utilities contribution
A7: Credit Union | B7: 2000 | C7: =B7/$B$2 -> 0.25437655 | D7: Savings & investments — auto-deducted
A8: Gym | B8: 400 | C8: =B8/$B$2 -> 0.05087531 | D8: Monthly membership
A9: Travel | B9: 500 | C9: =B9/$B$2 -> 0.063594137 | D9: Budgeted $500; actual range $260–$620
A10: Total Fixed Commitments | B10: =SUM(B6:B9) -> 3900 | C10: =B10/$B$2 -> 0.49603427
A12: Essential Needs
A13: Food & Dining | B13: 750 | C13: =B13/$B$2 -> 0.095391206 | D13: Lunches, snacks, personal groceries
A14: Phone & Data | B14: 200 | C14: =B14/$B$2 -> 0.025437655 | D14: Mobile plan & data
A15: Personal Care | B15: 250 | C15: =B15/$B$2 -> 0.031797069 | D15: Grooming, supplements, hygiene
A16: Total Essential Needs | B16: =SUM(B13:B15) -> 1200 | C16: =B16/$B$2 -> 0.15262593
A18: Lifestyle
A19: Entertainment | B19: 400 | C19: =B19/$B$2 -> 0.05087531 | D19: Going out, streaming, gaming
A20: Clothing & Shopping | B20: 300 | C20: =B20/$B$2 -> 0.038156482 | D20: Clothes, gear, miscellaneous
A21: Total Lifestyle | B21: =SUM(B19:B20) -> 700 | C21: =B21/$B$2 -> 0.089031792
A23: Wealth Building
A24: Emergency Fund | B24: 600 | C24: =B24/$B$2 -> 0.076312965 | D24: Target: ~$15,000 TTD (3-month buffer)
A25: Goals Fund | B25: 1462.36 | C25: =B25/$B$2 -> 0.18599504 | D25: Car, travel, future goals — remaining surplus
A26: Total Wealth Building | B26: =SUM(B24:B25) -> 2062.36 | C26: =B26/$B$2 -> 0.26230801
A28: GRAND TOTAL ALLOCATED | B28: =B10+B16+B21+B26 -> 7862.36 | C28: =B28/$B$2 -> 1
A29: Surplus / Unallocated | B29: =$B$2-B28 -> 0 | C29: =B29/$B$2 -> 0
A31: Savings & Wealth-Building Summary
B32: Monthly (TTD) | C32: Annual (TTD) | D32: % of Income
A33: Credit Union (savings/invest) | B33: =B7 -> 2000 | C33: =B7*12 -> 24000 | D33: =B7/$B$2 -> 0.25437655
A34: Emergency Fund contributions | B34: =B24 -> 600 | C34: =B24*12 -> 7200 | D34: =B24/$B$2 -> 0.076312965
A35: Goals Fund contributions | B35: =B25 -> 1462.36 | C35: =B25*12 -> 17548.32 | D35: =B25/$B$2 -> 0.18599504
A36: TOTAL SAVING / BUILDING WEALTH | B36: =B7+B24+B25 -> 4062.36 | C36: =(B7+B24+B25)*12 -> 48748.32 | D36: =(B7+B24+B25)/$B$2 -> 0.51668456
A38: Saving 51.7% of income ($4,062/mo). Once Emergency Fund hits $15,000 TTD (~25 months), redirect the $600/mo to Credit Union.

Sheet Log
A1: Expense Log · 2026 · Enter every transaction here (including fixed & savings transfers)
A2: Date | B2: Month | C2: Year | D2: Category | E2: Description / Notes | F2: Amount (TTD)
A3: 46174 | B3: =IF(A3<>"",TEXT(A3,"mmm"),"") -> Jun | C3: =IF(A3<>"",YEAR(A3),"") -> 2026 | D3: Credit Union | E3: Example: monthly credit union transfer | F3: 2000
B4: =IF(A4<>"",TEXT(A4,"mmm"),"") | C4: =IF(A4<>"",YEAR(A4),"")
B5: =IF(A5<>"",TEXT(A5,"mmm"),"") | C5: =IF(A5<>"",YEAR(A5),"")
B6: =IF(A6<>"",TEXT(A6,"mmm"),"") | C6: =IF(A6<>"",YEAR(A6),"")
B7: =IF(A7<>"",TEXT(A7,"mmm"),"") | C7: =IF(A7<>"",YEAR(A7),"")
B8: =IF(A8<>"",TEXT(A8,"mmm"),"") | C8: =IF(A8<>"",YEAR(A8),"")
B9: =IF(A9<>"",TEXT(A9,"mmm"),"") | C9: =IF(A9<>"",YEAR(A9),"")
B10: =IF(A10<>"",TEXT(A10,"mmm"),"") | C10: =IF(A10<>"",YEAR(A10),"")
B11: =IF(A11<>"",TEXT(A11,"mmm"),"") | C11: =IF(A11<>"",YEAR(A11),"")
B12: =IF(A12<>"",TEXT(A12,"mmm"),"") | C12: =IF(A12<>"",YEAR(A12),"")
B13: =IF(A13<>"",TEXT(A13,"mmm"),"") | C13: =IF(A13<>"",YEAR(A13),"")
B14: =IF(A14<>"",TEXT(A14,"mmm"),"") | C14: =IF(A14<>"",YEAR(A14),"")
B15: =IF(A15<>"",TEXT(A15,"mmm"),"") | C15: =IF(A15<>"",YEAR(A15),"")
... B502: =IF(A502<>"",TEXT(A502,"mmm"),"") | C502: =IF(A502<>"",YEAR(A502),"")

Sheet Monthly Summary
A1: Monthly Summary · Budget vs Actual · 2026
A3: Category | B3: Monthly Budget | C3: Jan | D3: Feb | E3: Mar | F3: Apr | G3: May | H3: Jun | I3: Jul | J3: Aug | K3: Sep | L3: Oct | M3: Nov | N3: Dec | O3: YTD Actual | P3: Annual Budget | Q3: YTD Variance
A4: House Contribution | B4: =Budget!$B$6 -> 1000 | C4: =IFERROR(SUMIFS(Log!$F:$F,Log!$D:$D,$A4,Log!$B:$B,"Jan",Log!$C:$C,2026),0) -> 0 | D4: =IFERROR(SUMIFS(Log!$F:$F,Log!$D:$D,$A4,Log!$B:$B,"Feb",Log!$C:$C,2026),0) -> 0 | E4: =IFERROR(SUMIFS(Log!$F:$F,Log!$D:$D,$A4,Log!$B:$B,"Mar",Log!$C:$C,2026),0) -> 0 | F4: =IFERROR(SUMIFS(Log!$F:$F,Log!$D:$D,$A4,Log!$B:$B,"Apr",Log!$C:$C,2026),0) -> 0 | G4: =IFERROR(SUMIFS(Log!$F:$F,Log!$D:$D,$A4,Log!$B:$B,"May",Log!$C:$C,2026),0) -> 0 | H4: =IFERROR(SUMIFS(Log!$F:$F,Log!$D:$D,$A4,Log!$B:$B,"Jun",Log!$C:$C,2026),0) -> 0 | I4: =IFERROR(SUMIFS(Log!$F:$F,Log!$D:$D,$A4,Log!$B:$B,"Jul",Log!$C:$C,2026),0) -> 0 | J4: =IFERROR(SUMIFS(Log!$F:$F,Log!$D:$D,$A4,Log!$B:$B,"Aug",Log!$C:$C,2026),0) -> 0 | K4: =IFERROR(SUMIFS(Log!$F:$F,Log!$D:$D,$A4,Log!$B:$B,"Sep",Log!$C:$C,2026),0) -> 0 | L4: =IFERROR(SUMIFS(Log!$F:$F,Log!$D:$D,$A4,Log!$B:$B,"Oct",Log!$C:$C,2026),0) -> 0 | M4: =IFERROR(SUMIFS(Log!$F:$F,Log!$D:$D,$A4,Log!$B:$B,"Nov",Log!$C:$C,2026),0) -> 0 | N4: =IFERROR(SUMIFS(Log!$F:$F,Log!$D:$D,$A4,Log!$B:$B,"Dec",Log!$C:$C,2026),0) -> 0 | O4: =SUM(C4:N4) -> 0 | P4: =$B4*12 -> 12000 | Q4: =P4-O4 -> 12000
A5: Credit Union | B5: =Budget!$B$7 -> 2000 | C5: =IFERROR(SUMIFS(Log!$F:$F,Log!$D:$D,$A5,Log!$B:$B,"Jan",Log!$C:$C,2026),0) -> 0 | D5: =IFERROR(SUMIFS(Log!$F:$F,Log!$D:$D,$A5,Log!$B:$B,"Feb",Log!$C:$C,2026),0) -> 0 | E5: =IFERROR(SUMIFS(Log!$F:$F,Log!$D:$D,$A5,Log!$B:$B,"Mar",Log!$C:$C,2026),0) -> 0 | F5: =IFERROR(SUMIFS(Log!$F:$F,Log!$D:$D,$A5,Log!$B:$B,"Apr",Log!$C:$C,2026),0) -> 0 | G5: =IFERROR(SUMIFS(Log!$F:$F,Log!$D:$D,$A5,Log!$B:$B,"May",Log!$C:$C,2026),0) -> 0 | H5: =IFERROR(SUMIFS(Log!$F:$F,Log!$D:$D,$A5,Log!$B:$B,"Jun",Log!$C:$C,2026),0) -> 2000 | I5: =IFERROR(SUMIFS(Log!$F:$F,Log!$D:$D,$A5,Log!$B:$B,"Jul",Log!$C:$C,2026),0) -> 0 | J5: =IFERROR(SUMIFS(Log!$F:$F,Log!$D:$D,$A5,Log!$B:$B,"Aug",Log!$C:$C,2026),0) -> 0 | K5: =IFERROR(SUMIFS(Log!$F:$F,Log!$D:$D,$A5,Log!$B:$B,"Sep",Log!$C:$C,2026),0) -> 0 | L5: =IFERROR(SUMIFS(Log!$F:$F,Log!$D:$D,$A5,Log!$B:$B,"Oct",Log!$C:$C,2026),0) -> 0 | M5: =IFERROR(SUMIFS(Log!$F:$F,Log!$D:$D,$A5,Log!$B:$B,"Nov",Log!$C:$C,2026),0) -> 0 | N5: =IFERROR(SUMIFS(Log!$F:$F,Log!$D:$D,$A5,Log!$B:$B,"Dec",Log!$C:$C,2026),0) -> 0 | O5: =SUM(C5:N5) -> 2000 | P5: =$B5*12 -> 24000 | Q5: =P5-O5 -> 22000
A6: Gym | B6: =Budget!$B$8 -> 400 | C6: =IFERROR(SUMIFS(Log!$F:$F,Log!$D:$D,$A6,Log!$B:$B,"Jan",Log!$C:$C,2026),0) -> 0 | D6: =IFERROR(SUMIFS(Log!$F:$F,Log!$D:$D,$A6,Log!$B:$B,"Feb",Log!$C:$C,2026),0) -> 0 | E6: =IFERROR(SUMIFS(Log!$F:$F,Log!$D:$D,$A6,Log!$B:$B,"Mar",Log!$C:$C,2026),0) -> 0 | F6: =IFERROR(SUMIFS(Log!$F:$F,Log!$D:$D,$A6,Log!$B:$B,"Apr",Log!$C:$C,2026),0) -> 0 | G6: =IFERROR(SUMIFS(Log!$F:$F,Log!$D:$D,$A6,Log!$B:$B,"May",Log!$C:$C,2026),0) -> 0 | H6: =IFERROR(SUMIFS(Log!$F:$F,Log!$D:$D,$A6,Log!$B:$B,"Jun",Log!$C:$C,2026),0) -> 0 | I6: =IFERROR(SUMIFS(Log!$F:$F,Log!$D:$D,$A6,Log!$B:$B,"Jul",Log!$C:$C,2026),0) -> 0 | J6: =IFERROR(SUMIFS(Log!$F:$F,Log!$D:$D,$A6,Log!$B:$B,"Aug",Log!$C:$C,2026),0) -> 0 | K6: =IFERROR(SUMIFS(Log!$F:$F,Log!$D:$D,$A6,Log!$B:$B,"Sep",Log!$C:$C,2026),0) -> 0 | L6: =IFERROR(SUMIFS(Log!$F:$F,Log!$D:$D,$A6,Log!$B:$B,"Oct",Log!$C:$C,2026),0) -> 0 | M6: =IFERROR(SUMIFS(Log!$F:$F,Log!$D:$D,$A6,Log!$B:$B,"Nov",Log!$C:$C,2026),0) -> 0 | N6: =IFERROR(SUMIFS(Log!$F:$F,Log!$D:$D,$A6,Log!$B:$B,"Dec",Log!$C:$C,2026),0) -> 0 | O6: =SUM(C6:N6) -> 0 | P6: =$B6*12 -> 4800 | Q6: =P6-O6 -> 4800
A7: Travel | B7: =Budget!$B$9 -> 500 | C7: =IFERROR(SUMIFS(Log!$F:$F,Log!$D:$D,$A7,Log!$B:$B,"Jan",Log!$C:$C,2026),0) -> 0 | D7: =IFERROR(SUMIFS(Log!$F:$F,Log!$D:$D,$A7,Log!$B:$B,"Feb",Log!$C:$C,2026),0) -> 0 | E7: =IFERROR(SUMIFS(Log!$F:$F,Log!$D:$D,$A7,Log!$B:$B,"Mar",Log!$C:$C,2026),0) -> 0 | F7: =IFERROR(SUMIFS(Log!$F:$F,Log!$D:$D,$A7,Log!$B:$B,"Apr",Log!$C:$C,2026),0) -> 0 | G7: =IFERROR(SUMIFS(Log!$F:$F,Log!$D:$D,$A7,Log!$B:$B,"May",Log!$C:$C,2026),0) -> 0 | H7: =IFERROR(SUMIFS(Log!$F:$F,Log!$D:$D,$A7,Log!$B:$B,"Jun",Log!$C:$C,2026),0) -> 0 | I7: =IFERROR(SUMIFS(Log!$F:$F,Log!$D:$D,$A7,Log!$B:$B,"Jul",Log!$C:$C,2026),0) -> 0 | J7: =IFERROR(SUMIFS(Log!$F:$F,Log!$D:$D,$A7,Log!$B:$B,"Aug",Log!$C:$C,2026),0) -> 0 | K7: =IFERROR(SUMIFS(Log!$F:$F,Log!$D:$D,$A7,Log!$B:$B,"Sep",Log!$C:$C,2026),0) -> 0 | L7: =IFERROR(SUMIFS(Log!$F:$F,Log!$D:$D,$A7,Log!$B:$B,"Oct",Log!$C:$C,2026),0) -> 0 | M7: =IFERROR(SUMIFS(Log!$F:$F,Log!$D:$D,$A7,Log!$B:$B,"Nov",Log!$C:$C,2026),0) -> 0 | N7: =IFERROR(SUMIFS(Log!$F:$F,Log!$D:$D,$A7,Log!$B:$B,"Dec",Log!$C:$C,2026),0) -> 0 | O7: =SUM(C7:N7) -> 0 | P7: =$B7*12 -> 6000 | Q7: =P7-O7 -> 6000
A8: Food & Dining | B8: =Budget!$B$13 -> 750 | C8: =IFERROR(SUMIFS(Log!$F:$F,Log!$D:$D,$A8,Log!$B:$B,"Jan",Log!$C:$C,2026),0) -> 0 | D8: =IFERROR(SUMIFS(Log!$F:$F,Log!$D:$D,$A8,Log!$B:$B,"Feb",Log!$C:$C,2026),0) -> 0 | E8: =IFERROR(SUMIFS(Log!$F:$F,Log!$D:$D,$A8,Log!$B:$B,"Mar",Log!$C:$C,2026),0) -> 0 | F8: =IFERROR(SUMIFS(Log!$F:$F,Log!$D:$D,$A8,Log!$B:$B,"Apr",Log!$C:$C,2026),0) -> 0 | G8: =IFERROR(SUMIFS(Log!$F:$F,Log!$D:$D,$A8,Log!$B:$B,"May",Log!$C:$C,2026),0) -> 0 | H8: =IFERROR(SUMIFS(Log!$F:$F,Log!$D:$D,$A8,Log!$B:$B,"Jun",Log!$C:$C,2026),0) -> 0 | I8: =IFERROR(SUMIFS(Log!$F:$F,Log!$D:$D,$A8,Log!$B:$B,"Jul",Log!$C:$C,2026),0) -> 0 | J8: =IFERROR(SUMIFS(Log!$F:$F,Log!$D:$D,$A8,Log!$B:$B,"Aug",Log!$C:$C,2026),0) -> 0 | K8: =IFERROR(SUMIFS(Log!$F:$F,Log!$D:$D,$A8,Log!$B:$B,"Sep",Log!$C:$C,2026),0) -> 0 | L8: =IFERROR(SUMIFS(Log!$F:$F,Log!$D:$D,$A8,Log!$B:$B,"Oct",Log!$C:$C,2026),0) -> 0 | M8: =IFERROR(SUMIFS(Log!$F:$F,Log!$D:$D,$A8,Log!$B:$B,"Nov",Log!$C:$C,2026),0) -> 0 | N8: =IFERROR(SUMIFS(Log!$F:$F,Log!$D:$D,$A8,Log!$B:$B,"Dec",Log!$C:$C,2026),0) -> 0 | O8: =SUM(C8:N8) -> 0 | P8: =$B8*12 -> 9000 | Q8: =P8-O8 -> 9000
A9: Phone & Data | B9: =Budget!$B$14 -> 200 | C9: =IFERROR(SUMIFS(Log!$F:$F,Log!$D:$D,$A9,Log!$B:$B,"Jan",Log!$C:$C,2026),0) -> 0 | D9: =IFERROR(SUMIFS(Log!$F:$F,Log!$D:$D,$A9,Log!$B:$B,"Feb",Log!$C:$C,2026),0) -> 0 | E9: =IFERROR(SUMIFS(Log!$F:$F,Log!$D:$D,$A9,Log!$B:$B,"Mar",Log!$C:$C,2026),0) -> 0 | F9: =IFERROR(SUMIFS(Log!$F:$F,Log!$D:$D,$A9,Log!$B:$B,"Apr",Log!$C:$C,2026),0) -> 0 | G9: =IFERROR(SUMIFS(Log!$F:$F,Log!$D:$D,$A9,Log!$B:$B,"May",Log!$C:$C,2026),0) -> 0 | H9: =IFERROR(SUMIFS(Log!$F:$F,Log!$D:$D,$A9,Log!$B:$B,"Jun",Log!$C:$C,2026),0) -> 0 | I9: =IFERROR(SUMIFS(Log!$F:$F,Log!$D:$D,$A9,Log!$B:$B,"Jul",Log!$C:$C,2026),0) -> 0 | J9: =IFERROR(SUMIFS(Log!$F:$F,Log!$D:$D,$A9,Log!$B:$B,"Aug",Log!$C:$C,2026),0) -> 0 | K9: =IFERROR(SUMIFS(Log!$F:$F,Log!$D:$D,$A9,Log!$B:$B,"Sep",Log!$C:$C,2026),0) -> 0 | L9: =IFERROR(SUMIFS(Log!$F:$F,Log!$D:$D,$A9,Log!$B:$B,"Oct",Log!$C:$C,2026),0) -> 0 | M9: =IFERROR(SUMIFS(Log!$F:$F,Log!$D:$D,$A9,Log!$B:$B,"Nov",Log!$C:$C,2026),0) -> 0 | N9: =IFERROR(SUMIFS(Log!$F:$F,Log!$D:$D,$A9,Log!$B:$B,"Dec",Log!$C:$C,2026),0) -> 0 | O9: =SUM(C9:N9) -> 0 | P9: =$B9*12 -> 2400 | Q9: =P9-O9 -> 2400
A10: Personal Care | B10: =Budget!$B$15 -> 250 | C10: =IFERROR(SUMIFS(Log!$F:$F,Log!$D:$D,$A10,Log!$B:$B,"Jan",Log!$C:$C,2026),0) -> 0 | D10: =IFERROR(SUMIFS(Log!$F:$F,Log!$D:$D,$A10,Log!$B:$B,"Feb",Log!$C:$C,2026),0) -> 0 | E10: =IFERROR(SUMIFS(Log!$F:$F,Log!$D:$D,$A10,Log!$B:$B,"Mar",Log!$C:$C,2026),0) -> 0 | F10: =IFERROR(SUMIFS(Log!$F:$F,Log!$D:$D,$A10,Log!$B:$B,"Apr",Log!$C:$C,2026),0) -> 0 | G10: =IFERROR(SUMIFS(Log!$F:$F,Log!$D:$D,$A10,Log!$B:$B,"May",Log!$C:$C,2026),0) -> 0 | H10: =IFERROR(SUMIFS(Log!$F:$F,Log!$D:$D,$A10,Log!$B:$B,"Jun",Log!$C:$C,2026),0) -> 0 | I10: =IFERROR(SUMIFS(Log!$F:$F,Log!$D:$D,$A10,Log!$B:$B,"Jul",Log!$C:$C,2026),0) -> 0 | J10: =IFERROR(SUMIFS(Log!$F:$F,Log!$D:$D,$A10,Log!$B:$B,"Aug",Log!$C:$C,2026),0) -> 0 | K10: =IFERROR(SUMIFS(Log!$F:$F,Log!$D:$D,$A10,Log!$B:$B,"Sep",Log!$C:$C,2026),0) -> 0 | L10: =IFERROR(SUMIFS(Log!$F:$F,Log!$D:$D,$A10,Log!$B:$B,"Oct",Log!$C:$C,2026),0) -> 0 | M10: =IFERROR(SUMIFS(Log!$F:$F,Log!$D:$D,$A10,Log!$B:$B,"Nov",Log!$C:$C,2026),0) -> 0 | N10: =IFERROR(SUMIFS(Log!$F:$F,Log!$D:$D,$A10,Log!$B:$B,"Dec",Log!$C:$C,2026),0) -> 0 | O10: =SUM(C10:N10) -> 0 | P10: =$B10*12 -> 3000 | Q10: =P10-O10 -> 3000
A11: Entertainment | B11: =Budget!$B$19 -> 400 | C11: =IFERROR(SUMIFS(Log!$F:$F,Log!$D:$D,$A11,Log!$B:$B,"Jan",Log!$C:$C,2026),0) -> 0 | D11: =IFERROR(SUMIFS(Log!$F:$F,Log!$D:$D,$A11,Log!$B:$B,"Feb",Log!$C:$C,2026),0) -> 0 | E11: =IFERROR(SUMIFS(Log!$F:$F,Log!$D:$D,$A11,Log!$B:$B,"Mar",Log!$C:$C,2026),0) -> 0 | F11: =IFERROR(SUMIFS(Log!$F:$F,Log!$D:$D,$A11,Log!$B:$B,"Apr",Log!$C:$C,2026),0) -> 0 | G11: =IFERROR(SUMIFS(Log!$F:$F,Log!$D:$D,$A11,Log!$B:$B,"May",Log!$C:$C,2026),0) -> 0 | H11: =IFERROR(SUMIFS(Log!$F:$F,Log!$D:$D,$A11,Log!$B:$B,"Jun",Log!$C:$C,2026),0) -> 0 | I11: =IFERROR(SUMIFS(Log!$F:$F,Log!$D:$D,$A11,Log!$B:$B,"Jul",Log!$C:$C,2026),0) -> 0 | J11: =IFERROR(SUMIFS(Log!$F:$F,Log!$D:$D,$A11,Log!$B:$B,"Aug",Log!$C:$C,2026),0) -> 0 | K11: =IFERROR(SUMIFS(Log!$F:$F,Log!$D:$D,$A11,Log!$B:$B,"Sep",Log!$C:$C,2026),0) -> 0 | L11: =IFERROR(SUMIFS(Log!$F:$F,Log!$D:$D,$A11,Log!$B:$B,"Oct",Log!$C:$C,2026),0) -> 0 | M11: =IFERROR(SUMIFS(Log!$F:$F,Log!$D:$D,$A11,Log!$B:$B,"Nov",Log!$C:$C,2026),0) -> 0 | N11: =IFERROR(SUMIFS(Log!$F:$F,Log!$D:$D,$A11,Log!$B:$B,"Dec",Log!$C:$C,2026),0) -> 0 | O11: =SUM(C11:N11) -> 0 | P11: =$B11*12 -> 4800 | Q11: =P11-O11 -> 4800
A12: Clothing & Shopping | B12: =Budget!$B$20 -> 300 | C12: =IFERROR(SUMIFS(Log!$F:$F,Log!$D:$D,$A12,Log!$B:$B,"Jan",Log!$C:$C,2026),0) -> 0 | D12: =IFERROR(SUMIFS(Log!$F:$F,Log!$D:$D,$A12,Log!$B:$B,"Feb",Log!$C:$C,2026),0) -> 0 | E12: =IFERROR(SUMIFS(Log!$F:$F,Log!$D:$D,$A12,Log!$B:$B,"Mar",Log!$C:$C,2026),0) -> 0 | F12: =IFERROR(SUMIFS(Log!$F:$F,Log!$D:$D,$A12,Log!$B:$B,"Apr",Log!$C:$C,2026),0) -> 0 | G12: =IFERROR(SUMIFS(Log!$F:$F,Log!$D:$D,$A12,Log!$B:$B,"May",Log!$C:$C,2026),0) -> 0 | H12: =IFERROR(SUMIFS(Log!$F:$F,Log!$D:$D,$A12,Log!$B:$B,"Jun",Log!$C:$C,2026),0) -> 0 | I12: =IFERROR(SUMIFS(Log!$F:$F,Log!$D:$D,$A12,Log!$B:$B,"Jul",Log!$C:$C,2026),0) -> 0 | J12: =IFERROR(SUMIFS(Log!$F:$F,Log!$D:$D,$A12,Log!$B:$B,"Aug",Log!$C:$C,2026),0) -> 0 | K12: =IFERROR(SUMIFS(Log!$F:$F,Log!$D:$D,$A12,Log!$B:$B,"Sep",Log!$C:$C,2026),0) -> 0 | L12: =IFERROR(SUMIFS(Log!$F:$F,Log!$D:$D,$A12,Log!$B:$B,"Oct",Log!$C:$C,2026),0) -> 0 | M12: =IFERROR(SUMIFS(Log!$F:$F,Log!$D:$D,$A12,Log!$B:$B,"Nov",Log!$C:$C,2026),0) -> 0 | N12: =IFERROR(SUMIFS(Log!$F:$F,Log!$D:$D,$A12,Log!$B:$B,"Dec",Log!$C:$C,2026),0) -> 0 | O12: =SUM(C12:N12) -> 0 | P12: =$B12*12 -> 3600 | Q12: =P12-O12 -> 3600
A13: Emergency Fund | B13: =Budget!$B$24 -> 600 | C13: =IFERROR(SUMIFS(Log!$F:$F,Log!$D:$D,$A13,Log!$B:$B,"Jan",Log!$C:$C,2026),0) -> 0 | D13: =IFERROR(SUMIFS(Log!$F:$F,Log!$D:$D,$A13,Log!$B:$B,"Feb",Log!$C:$C,2026),0) -> 0 | E13: =IFERROR(SUMIFS(Log!$F:$F,Log!$D:$D,$A13,Log!$B:$B,"Mar",Log!$C:$C,2026),0) -> 0 | F13: =IFERROR(SUMIFS(Log!$F:$F,Log!$D:$D,$A13,Log!$B:$B,"Apr",Log!$C:$C,2026),0) -> 0 | G13: =IFERROR(SUMIFS(Log!$F:$F,Log!$D:$D,$A13,Log!$B:$B,"May",Log!$C:$C,2026),0) -> 0 | H13: =IFERROR(SUMIFS(Log!$F:$F,Log!$D:$D,$A13,Log!$B:$B,"Jun",Log!$C:$C,2026),0) -> 0 | I13: =IFERROR(SUMIFS(Log!$F:$F,Log!$D:$D,$A13,Log!$B:$B,"Jul",Log!$C:$C,2026),0) -> 0 | J13: =IFERROR(SUMIFS(Log!$F:$F,Log!$D:$D,$A13,Log!$B:$B,"Aug",Log!$C:$C,2026),0) -> 0 | K13: =IFERROR(SUMIFS(Log!$F:$F,Log!$D:$D,$A13,Log!$B:$B,"Sep",Log!$C:$C,2026),0) -> 0 | L13: =IFERROR(SUMIFS(Log!$F:$F,Log!$D:$D,$A13,Log!$B:$B,"Oct",Log!$C:$C,2026),0) -> 0 | M13: =IFERROR(SUMIFS(Log!$F:$F,Log!$D:$D,$A13,Log!$B:$B,"Nov",Log!$C:$C,2026),0) -> 0 | N13: =IFERROR(SUMIFS(Log!$F:$F,Log!$D:$D,$A13,Log!$B:$B,"Dec",Log!$C:$C,2026),0) -> 0 | O13: =SUM(C13:N13) -> 0 | P13: =$B13*12 -> 7200 | Q13: =P13-O13 -> 7200
A14: Goals Fund | B14: =Budget!$B$25 -> 1462.36 | C14: =IFERROR(SUMIFS(Log!$F:$F,Log!$D:$D,$A14,Log!$B:$B,"Jan",Log!$C:$C,2026),0) -> 0 | D14: =IFERROR(SUMIFS(Log!$F:$F,Log!$D:$D,$A14,Log!$B:$B,"Feb",Log!$C:$C,2026),0) -> 0 | E14: =IFERROR(SUMIFS(Log!$F:$F,Log!$D:$D,$A14,Log!$B:$B,"Mar",Log!$C:$C,2026),0) -> 0 | F14: =IFERROR(SUMIFS(Log!$F:$F,Log!$D:$D,$A14,Log!$B:$B,"Apr",Log!$C:$C,2026),0) -> 0 | G14: =IFERROR(SUMIFS(Log!$F:$F,Log!$D:$D,$A14,Log!$B:$B,"May",Log!$C:$C,2026),0) -> 0 | H14: =IFERROR(SUMIFS(Log!$F:$F,Log!$D:$D,$A14,Log!$B:$B,"Jun",Log!$C:$C,2026),0) -> 0 | I14: =IFERROR(SUMIFS(Log!$F:$F,Log!$D:$D,$A14,Log!$B:$B,"Jul",Log!$C:$C,2026),0) -> 0 | J14: =IFERROR(SUMIFS(Log!$F:$F,Log!$D:$D,$A14,Log!$B:$B,"Aug",Log!$C:$C,2026),0) -> 0 | K14: =IFERROR(SUMIFS(Log!$F:$F,Log!$D:$D,$A14,Log!$B:$B,"Sep",Log!$C:$C,2026),0) -> 0 | L14: =IFERROR(SUMIFS(Log!$F:$F,Log!$D:$D,$A14,Log!$B:$B,"Oct",Log!$C:$C,2026),0) -> 0 | M14: =IFERROR(SUMIFS(Log!$F:$F,Log!$D:$D,$A14,Log!$B:$B,"Nov",Log!$C:$C,2026),0) -> 0 | N14: =IFERROR(SUMIFS(Log!$F:$F,Log!$D:$D,$A14,Log!$B:$B,"Dec",Log!$C:$C,2026),0) -> 0 | O14: =SUM(C14:N14) -> 0 | P14: =$B14*12 -> 17548.32 | Q14: =P14-O14 -> 17548.32
A15: Other | B15: =0 -> 0 | C15: =IFERROR(SUMIFS(Log!$F:$F,Log!$D:$D,$A15,Log!$B:$B,"Jan",Log!$C:$C,2026),0) -> 0 | D15: =IFERROR(SUMIFS(Log!$F:$F,Log!$D:$D,$A15,Log!$B:$B,"Feb",Log!$C:$C,2026),0) -> 0 | E15: =IFERROR(SUMIFS(Log!$F:$F,Log!$D:$D,$A15,Log!$B:$B,"Mar",Log!$C:$C,2026),0) -> 0 | F15: =IFERROR(SUMIFS(Log!$F:$F,Log!$D:$D,$A15,Log!$B:$B,"Apr",Log!$C:$C,2026),0) -> 0 | G15: =IFERROR(SUMIFS(Log!$F:$F,Log!$D:$D,$A15,Log!$B:$B,"May",Log!$C:$C,2026),0) -> 0 | H15: =IFERROR(SUMIFS(Log!$F:$F,Log!$D:$D,$A15,Log!$B:$B,"Jun",Log!$C:$C,2026),0) -> 0 | I15: =IFERROR(SUMIFS(Log!$F:$F,Log!$D:$D,$A15,Log!$B:$B,"Jul",Log!$C:$C,2026),0) -> 0 | J15: =IFERROR(SUMIFS(Log!$F:$F,Log!$D:$D,$A15,Log!$B:$B,"Aug",Log!$C:$C,2026),0) -> 0 | K15: =IFERROR(SUMIFS(Log!$F:$F,Log!$D:$D,$A15,Log!$B:$B,"Sep",Log!$C:$C,2026),0) -> 0 | L15: =IFERROR(SUMIFS(Log!$F:$F,Log!$D:$D,$A15,Log!$B:$B,"Oct",Log!$C:$C,2026),0) -> 0 | M15: =IFERROR(SUMIFS(Log!$F:$F,Log!$D:$D,$A15,Log!$B:$B,"Nov",Log!$C:$C,2026),0) -> 0 | N15: =IFERROR(SUMIFS(Log!$F:$F,Log!$D:$D,$A15,Log!$B:$B,"Dec",Log!$C:$C,2026),0) -> 0 | O15: =SUM(C15:N15) -> 0 | P15: =$B15*12 -> 0 | Q15: =P15-O15 -> 0
A16: MONTHLY TOTAL | B16: =SUM(B4:B15) -> 7862.36 | C16: =SUM(C4:C15) -> 0 | D16: =SUM(D4:D15) -> 0 | E16: =SUM(E4:E15) -> 0 | F16: =SUM(F4:F15) -> 0 | G16: =SUM(G4:G15) -> 0 | H16: =SUM(H4:H15) -> 2000 | I16: =SUM(I4:I15) -> 0 | ... Q16: =SUM(Q4:Q15) -> 92348.32
A17: Monthly income (budget) | B17: =Budget!$B$2 -> 7862.36 | C17: =Budget!$B$2 -> 7862.36 | D17: =Budget!$B$2 -> 7862.36 | E17: =Budget!$B$2 -> 7862.36 | F17: =Budget!$B$2 -> 7862.36 | G17: =Budget!$B$2 -> 7862.36 | H17: =Budget!$B$2 -> 7862.36 | I17: =Budget!$B$2 -> 7862.36 | ... N17: =Budget!$B$2 -> 7862.36
A18: Over / Under budget (+under, -over) | C18: =IF(C17=0,"",C17-C16) -> 7862.36 | D18: =IF(D17=0,"",D17-D16) -> 7862.36 | E18: =IF(E17=0,"",E17-E16) -> 7862.36 | F18: =IF(F17=0,"",F17-F16) -> 7862.36 | G18: =IF(G17=0,"",G17-G16) -> 7862.36 | H18: =IF(H17=0,"",H17-H16) -> 5862.36 | I18: =IF(I17=0,"",I17-I16) -> 7862.36 | J18: =IF(J17=0,"",J17-J16) -> 7862.36 | ... N18: =IF(N17=0,"",N17-N16) -> 7862.36
A21: Blue text = hardcoded inputs you can change. Black text = auto-calculated. Log ALL spending in the Log sheet (including Credit Union & savings transfers).

Sheet Savings Tracker
A1: Savings & Wealth-Building Tracker · 2026
A3: Month | B3: Credit Union | D3: Emergency Fund | F3: Goals Fund | H3: Total Saved
A4: Month | B4: Contributed | C4: Balance | D4: Contributed | E4: Balance | F4: Contributed | G4: Balance | H4: Running Total
A5: Jan | B5: =Budget!$B$7 -> 2000 | C5: =B5 -> 2000 | D5: =Budget!$B$24 -> 600 | E5: =D5 -> 600 | F5: =Budget!$B$25 -> 1462.36 | G5: =F5 -> 1462.36 | H5: =C5+E5+G5 -> 4062.36
A6: Feb | B6: =Budget!$B$7 -> 2000 | C6: =C5+B6 -> 4000 | D6: =Budget!$B$24 -> 600 | E6: =E5+D6 -> 1200 | F6: =Budget!$B$25 -> 1462.36 | G6: =G5+F6 -> 2924.72 | H6: =C6+E6+G6 -> 8124.72
A7: Mar | B7: =Budget!$B$7 -> 2000 | C7: =C6+B7 -> 6000 | D7: =Budget!$B$24 -> 600 | E7: =E6+D7 -> 1800 | F7: =Budget!$B$25 -> 1462.36 | G7: =G6+F7 -> 4387.08 | H7: =C7+E7+G7 -> 12187.08
A8: Apr | B8: =Budget!$B$7 -> 2000 | C8: =C7+B8 -> 8000 | D8: =Budget!$B$24 -> 600 | E8: =E7+D8 -> 2400 | F8: =Budget!$B$25 -> 1462.36 | G8: =G7+F8 -> 5849.44 | H8: =C8+E8+G8 -> 16249.44
A9: May | B9: =Budget!$B$7 -> 2000 | C9: =C8+B9 -> 10000 | D9: =Budget!$B$24 -> 600 | E9: =E8+D9 -> 3000 | F9: =Budget!$B$25 -> 1462.36 | G9: =G8+F9 -> 7311.8 | H9: =C9+E9+G9 -> 20311.8
A10: Jun | B10: =Budget!$B$7 -> 2000 | C10: =C9+B10 -> 12000 | D10: =Budget!$B$24 -> 600 | E10: =E9+D10 -> 3600 | F10: =Budget!$B$25 -> 1462.36 | G10: =G9+F10 -> 8774.16 | H10: =C10+E10+G10 -> 24374.16
A11: Jul | B11: =Budget!$B$7 -> 2000 | C11: =C10+B11 -> 14000 | D11: =Budget!$B$24 -> 600 | E11: =E10+D11 -> 4200 | F11: =Budget!$B$25 -> 1462.36 | G11: =G10+F11 -> 10236.52 | H11: =C11+E11+G11 -> 28436.52
A12: Aug | B12: =Budget!$B$7 -> 2000 | C12: =C11+B12 -> 16000 | D12: =Budget!$B$24 -> 600 | E12: =E11+D12 -> 4800 | F12: =Budget!$B$25 -> 1462.36 | G12: =G11+F12 -> 11698.88 | H12: =C12+E12+G12 -> 32498.88
A13: Sep | B13: =Budget!$B$7 -> 2000 | C13: =C12+B13 -> 18000 | D13: =Budget!$B$24 -> 600 | E13: =E12+D13 -> 5400 | F13: =Budget!$B$25 -> 1462.36 | G13: =G12+F13 -> 13161.24 | H13: =C13+E13+G13 -> 36561.24
A14: Oct | B14: =Budget!$B$7 -> 2000 | C14: =C13+B14 -> 20000 | D14: =Budget!$B$24 -> 600 | E14: =E13+D14 -> 6000 | F14: =Budget!$B$25 -> 1462.36 | G14: =G13+F14 -> 14623.6 | H14: =C14+E14+G14 -> 40623.6
A15: Nov | B15: =Budget!$B$7 -> 2000 | C15: =C14+B15 -> 22000 | D15: =Budget!$B$24 -> 600 | E15: =E14+D15 -> 6600 | F15: =Budget!$B$25 -> 1462.36 | G15: =G14+F15 -> 16085.96 | H15: =C15+E15+G15 -> 44685.96
A16: Dec | B16: =Budget!$B$7 -> 2000 | C16: =C15+B16 -> 24000 | D16: =Budget!$B$24 -> 600 | E16: =E15+D16 -> 7200 | F16: =Budget!$B$25 -> 1462.36 | G16: =G15+F16 -> 17548.32 | H16: =C16+E16+G16 -> 48748.32
A17: Year End | B17: =SUM(B5:B16) -> 24000 | C17: =C16 -> 24000 | D17: =SUM(D5:D16) -> 7200 | E17: =E16 -> 7200 | F17: =SUM(F5:F16) -> 17548.32 | G17: =G16 -> 17548.32 | H17: =H16 -> 48748.32
A19: Emergency Fund target: $15,000 TTD (3-month buffer) · At $600/mo you hit this around month 25 (Feb 2028). Once reached, redirect the $600/mo to Credit Union.
A21: Blue text = editable inputs. Override any month's contribution if actual amount differs from budget.
